fmpy_stark/__init__.py
fmpy_stark/client.py
fmpy_stark/client_legacy.py
fmpy_stark/config.py
fmpy_stark/exceptions.py
fmpy_stark/utils.py
fmpy_stark/endpoints/__init__.py
fmpy_stark/endpoints/analyst.py
fmpy_stark/endpoints/bulk.py
fmpy_stark/endpoints/calendar.py
fmpy_stark/endpoints/chart.py
fmpy_stark/endpoints/company.py
fmpy_stark/endpoints/crypto.py
fmpy_stark/endpoints/directory.py
fmpy_stark/endpoints/etf.py
fmpy_stark/endpoints/forex.py
fmpy_stark/endpoints/news.py
fmpy_stark/endpoints/quote.py
fmpy_stark/endpoints/search.py
fmpy_stark/endpoints/sec.py
fmpy_stark/endpoints/statements.py
fmpy_stark/endpoints_legacy/__init__.py
fmpy_stark/endpoints_legacy/bulk.py
fmpy_stark-0.1.1.dist-info/licenses/LICENSE
fmpy_stark-0.1.1.dist-info/METADATA
fmpy_stark-0.1.1.dist-info/WHEEL
fmpy_stark-0.1.1.dist-info/top_level.txt
fmpy_stark-0.1.1.dist-info/RECORD
