Metadata-Version: 2.4
Name: fmpy_stark
Version: 0.1.1
Summary: Python SDK for Financial Modeling Prep API
Home-page: https://github.com/stark-tech-space/fmpy
Author: Jimmy
Author-email: Jimmy <skylinezum@noreply.github.com>
License: The Unlicense
Project-URL: Homepage, https://github.com/yourusername/fmpy
Project-URL: Bug Tracker, https://github.com/yourusername/fmpy/issues
Project-URL: Documentation, https://fmpy.readthedocs.io/
Classifier: Programming Language :: Python :: 3
Classifier: Programming Language :: Python :: 3.12
Classifier: License :: OSI Approved :: The Unlicense (Unlicense)
Classifier: Operating System :: OS Independent
Classifier: Intended Audience :: Financial and Insurance Industry
Classifier: Intended Audience :: Developers
Classifier: Topic :: Office/Business :: Financial :: Investment
Classifier: Topic :: Software Development :: Libraries :: Python Modules
Requires-Python: >=3.12
License-File: LICENSE
Requires-Dist: requests>=2.32.3
Requires-Dist: pandas>=2.2.3
Requires-Dist: python-dateutil>=2.8.0
Provides-Extra: dev
Requires-Dist: pytest>=6.0.0; extra == "dev"
Requires-Dist: pytest-cov>=2.12.0; extra == "dev"
Requires-Dist: black>=21.5b2; extra == "dev"
Requires-Dist: isort>=5.9.1; extra == "dev"
Requires-Dist: mypy>=0.812; extra == "dev"
Requires-Dist: flake8>=3.9.2; extra == "dev"
Provides-Extra: docs
Requires-Dist: sphinx>=4.0.2; extra == "docs"
Requires-Dist: sphinx-rtd-theme>=0.5.2; extra == "docs"
Dynamic: author
Dynamic: home-page
Dynamic: license-file
Dynamic: requires-python
